{"telem": {"takim_numarasi": 9, "iha_enlem": 40.2327439, "iha_boylam": 29.0073198, "iha_irtifa": 76.605, "iha_dikilme": 2.929, "iha_yonelme": 236.0, "iha_yatis": -12.854, "iha_hiz": 12.509, "iha_kilitlenme": 0, "iha_batarya": 39, "iha_otonom": 1, "hedef_merkez_X": 0, "hedef_merkez_Y": 0, "hedef_genislik": 0, "hedef_yukseklik": 0, "gps_saati": {"saat": 8, "dakika": 48, "saniye": 15, "milisaniye": 951}, "IHA_kilitlenme": 0}, "Others": {"Servo": {"Servo1": 1434, "Servo2": 1374, "Servo3": 1653, "Servo4": 1526, "Servo5": 1434, "Servo6": 0, "Servo7": 0, "Servo8": 0}, "Channel": {"Channel1": 1430, "Channel2": 1378, "Channel3": 1593, "Channel4": 1517, "Channel5": 1996, "Channel6": 992, "Channel7": 1996, "Channel8": 1560}, "WindData": {"WindSpeed": 6.978484630584717, "WindDirection": 256.6387405395508}, "Mode": "AUTO"}, "uniData": {"Heading": 236.0, "Roll": -12.854, "VerticalSpeed": 0.904, "AirSpeed": 18.38}}
