{"telem": {"takim_numarasi": 9, "iha_enlem": 40.2320214, "iha_boylam": 29.0079615, "iha_irtifa": 78.29, "iha_dikilme": 11.633, "iha_yonelme": 316.0, "iha_yatis": -4.55, "iha_hiz": 10.467, "iha_kilitlenme": 0, "iha_batarya": 71, "iha_otonom": 1, "hedef_merkez_X": 0, "hedef_merkez_Y": 0, "hedef_genislik": 0, "hedef_yukseklik": 0, "gps_saati": {"saat": 8, "dakika": 42, "saniye": 46, "milisaniye": 210}, "IHA_kilitlenme": 0}, "Others": {"Servo": {"Servo1": 1537, "Servo2": 1364, "Servo3": 1492, "Servo4": 1646, "Servo5": 1537, "Servo6": 0, "Servo7": 0, "Servo8": 0}, "Channel": {"Channel1": 1492, "Channel2": 1416, "Channel3": 1532, "Channel4": 1500, "Channel5": 992, "Channel6": 992, "Channel7": 1996, "Channel8": 1560}, "WindData": {"WindSpeed": 5.853497505187988, "WindDirection": 261.25730895996094}, "Mode": "AUTO"}, "uniData": {"Heading": 316.0, "Roll": -4.55, "VerticalSpeed": 3.25, "AirSpeed": 15.848}}
