{"telem": {"takim_numarasi": 9, "iha_enlem": 40.2319787, "iha_boylam": 29.0078116, "iha_irtifa": 79.578, "iha_dikilme": 6.792, "iha_yonelme": 332.0, "iha_yatis": 11.537, "iha_hiz": 14.905, "iha_kilitlenme": 0, "iha_batarya": 81, "iha_otonom": 1, "hedef_merkez_X": 0, "hedef_merkez_Y": 0, "hedef_genislik": 0, "hedef_yukseklik": 0, "gps_saati": {"saat": 8, "dakika": 43, "saniye": 55, "milisaniye": 450}, "IHA_kilitlenme": 0}, "Others": {"Servo": {"Servo1": 1570, "Servo2": 1389, "Servo3": 1325, "Servo4": 1628, "Servo5": 1570, "Servo6": 0, "Servo7": 0, "Servo8": 0}, "Channel": {"Channel1": 1492, "Channel2": 1416, "Channel3": 1532, "Channel4": 1500, "Channel5": 992, "Channel6": 992, "Channel7": 1996, "Channel8": 1560}, "WindData": {"WindSpeed": 5.410427093505859, "WindDirection": 258.3029327392578}, "Mode": "AUTO"}, "uniData": {"Heading": 332.0, "Roll": 11.537, "VerticalSpeed": 1.995, "AirSpeed": 16.672}}
