{"telem": {"takim_numarasi": 9, "iha_enlem": 40.2307976, "iha_boylam": 29.0050761, "iha_irtifa": 77.565, "iha_dikilme": 8.82, "iha_yonelme": 151.0, "iha_yatis": -40.996, "iha_hiz": 18.614, "iha_kilitlenme": 0, "iha_batarya": 59, "iha_otonom": 1, "hedef_merkez_X": 0, "hedef_merkez_Y": 0, "hedef_genislik": 0, "hedef_yukseklik": 0, "gps_saati": {"saat": 8, "dakika": 48, "saniye": 54, "milisaniye": 710}, "IHA_kilitlenme": 0}, "Others": {"Servo": {"Servo1": 1602, "Servo2": 1404, "Servo3": 1463, "Servo4": 1651, "Servo5": 1602, "Servo6": 0, "Servo7": 0, "Servo8": 0}, "Channel": {"Channel1": 1500, "Channel2": 1500, "Channel3": 1499, "Channel4": 1543, "Channel5": 1996, "Channel6": 992, "Channel7": 1996, "Channel8": 1560}, "WindData": {"WindSpeed": 7.1644287109375, "WindDirection": 249.22821807861328}, "Mode": "AUTO"}, "uniData": {"Heading": 151.0, "Roll": -40.996, "VerticalSpeed": 2.836, "AirSpeed": 19.214}}
