{"telem": {"takim_numarasi": 9, "iha_enlem": 40.2315264, "iha_boylam": 29.0080754, "iha_irtifa": 86.604, "iha_dikilme": -0.937, "iha_yonelme": 316.0, "iha_yatis": -0.599, "iha_hiz": 12.777, "iha_kilitlenme": 0, "iha_batarya": 79, "iha_otonom": 1, "hedef_merkez_X": 0, "hedef_merkez_Y": 0, "hedef_genislik": 0, "hedef_yukseklik": 0, "gps_saati": {"saat": 8, "dakika": 43, "saniye": 51, "milisaniye": 451}, "IHA_kilitlenme": 0}, "Others": {"Servo": {"Servo1": 1549, "Servo2": 1388, "Servo3": 1294, "Servo4": 1618, "Servo5": 1549, "Servo6": 0, "Servo7": 0, "Servo8": 0}, "Channel": {"Channel1": 1492, "Channel2": 1416, "Channel3": 1532, "Channel4": 1500, "Channel5": 992, "Channel6": 992, "Channel7": 1996, "Channel8": 1560}, "WindData": {"WindSpeed": 5.4228692054748535, "WindDirection": 256.44529724121094}, "Mode": "AUTO"}, "uniData": {"Heading": 316.0, "Roll": -0.599, "VerticalSpeed": -0.253, "AirSpeed": 15.459}}
