{"sunucusaati":{"gun":18,"saat":8,"dakika":54,"saniye":16,"milisaniye":902},"konumBilgileri":[{"takim_numarasi":1,"iha_enlem":40.23105,"iha_boylam":29.0079937,"iha_irtifa":77.11,"iha_dikilme":3.74,"iha_yonelme":81.17,"iha_yatis":15.99,"iha_hizi":24.91,"zaman_farki":-294},{"takim_numarasi":4,"iha_enlem":40.231987,"iha_boylam":29.0071659,"iha_irtifa":61.439,"iha_dikilme":-1.0,"iha_yonelme":284.0,"iha_yatis":9.0,"iha_hizi":25.0,"zaman_farki":44949},{"takim_numarasi":6,"iha_enlem":40.2320137,"iha_boylam":29.0075817,"iha_irtifa":104.0,"iha_dikilme":0.0,"iha_yonelme":339.0,"iha_yatis":32.0,"iha_hizi":19.0,"zaman_farki":-141},{"takim_numarasi":8,"iha_enlem":40.23083,"iha_boylam":29.0068951,"iha_irtifa":105.38,"iha_dikilme":11.2174063,"iha_yonelme":304.6,"iha_yatis":17.69806,"iha_hizi":13.97,"zaman_farki":-300},{"takim_numarasi":10,"iha_enlem":40.23101,"iha_boylam":29.0087051,"iha_irtifa":8.9,"iha_dikilme":0.0,"iha_yonelme":21.0,"iha_yatis":-8.0,"iha_hizi":68.0,"zaman_farki":-98},{"takim_numarasi":11,"iha_enlem":40.23234,"iha_boylam":29.00568,"iha_irtifa":47.0,"iha_dikilme":9.0,"iha_yonelme":323.0,"iha_yatis":51.0,"iha_hizi":21.0,"zaman_farki":394},{"takim_numarasi":12,"iha_enlem":40.23259,"iha_boylam":29.0085545,"iha_irtifa":48.0,"iha_dikilme":4.0,"iha_yonelme":190.0,"iha_yatis":47.0,"iha_hizi":19.0,"zaman_farki":286},{"takim_numarasi":13,"iha_enlem":40.2321243,"iha_boylam":29.0079727,"iha_irtifa":96.11,"iha_dikilme":-3.79780865,"iha_yonelme":147.39296,"iha_yatis":39.6193733,"iha_hizi":23.0361843,"zaman_farki":641},{"takim_numarasi":14,"iha_enlem":40.2314835,"iha_boylam":29.0059624,"iha_irtifa":98.342,"iha_dikilme":0.0,"iha_yonelme":291.0,"iha_yatis":-3.0,"iha_hizi":21.0,"zaman_farki":49},{"takim_numarasi":18,"iha_enlem":40.2313576,"iha_boylam":29.009079,"iha_irtifa":-0.071,"iha_dikilme":-11.1925449,"iha_yonelme":353.710541,"iha_yatis":12.1959143,"iha_hizi":0.02,"zaman_farki":558577},{"takim_numarasi":22,"iha_enlem":40.2319,"iha_boylam":29.0076733,"iha_irtifa":94.0,"iha_dikilme":36.0,"iha_yonelme":113.0,"iha_yatis":-5.0,"iha_hizi":17.0,"zaman_farki":953}]}
