{"sunucusaati":{"gun":18,"saat":9,"dakika":5,"saniye":7,"milisaniye":708},"konumBilgileri":[{"takim_numarasi":1,"iha_enlem":40.2319069,"iha_boylam":29.008316,"iha_irtifa":78.81,"iha_dikilme":1.33,"iha_yonelme":288.63,"iha_yatis":18.18,"iha_hizi":17.86,"zaman_farki":512},{"takim_numarasi":4,"iha_enlem":40.23169,"iha_boylam":29.0094166,"iha_irtifa":0.084,"iha_dikilme":2.0,"iha_yonelme":34.0,"iha_yatis":0.0,"iha_hizi":0.0,"zaman_farki":217995},{"takim_numarasi":6,"iha_enlem":40.2319679,"iha_boylam":29.0066242,"iha_irtifa":126.0,"iha_dikilme":0.0,"iha_yonelme":350.0,"iha_yatis":38.0,"iha_hizi":19.0,"zaman_farki":-139},{"takim_numarasi":8,"iha_enlem":40.2304573,"iha_boylam":29.0090313,"iha_irtifa":22.865,"iha_dikilme":11.0617847,"iha_yonelme":356.45,"iha_yatis":-3.16021061,"iha_hizi":13.16,"zaman_farki":507},{"takim_numarasi":10,"iha_enlem":40.23176,"iha_boylam":29.0092125,"iha_irtifa":0.7,"iha_dikilme":0.0,"iha_yonelme":274.0,"iha_yatis":0.0,"iha_hizi":26.0,"zaman_farki":644708},{"takim_numarasi":11,"iha_enlem":40.2324,"iha_boylam":29.00619,"iha_irtifa":97.0,"iha_dikilme":-1.0,"iha_yonelme":245.0,"iha_yatis":-56.0,"iha_hizi":20.0,"zaman_farki":98},{"takim_numarasi":12,"iha_enlem":40.2313957,"iha_boylam":29.006731,"iha_irtifa":64.0,"iha_dikilme":2.0,"iha_yonelme":297.0,"iha_yatis":31.0,"iha_hizi":17.0,"zaman_farki":4852},{"takim_numarasi":13,"iha_enlem":40.23195,"iha_boylam":29.0046444,"iha_irtifa":49.83,"iha_dikilme":2.80816579,"iha_yonelme":200.89621,"iha_yatis":24.99306,"iha_hizi":16.8399925,"zaman_farki":588},{"takim_numarasi":14,"iha_enlem":40.2329254,"iha_boylam":29.0093269,"iha_irtifa":-0.385,"iha_dikilme":-5.0,"iha_yonelme":295.0,"iha_yatis":22.0,"iha_hizi":1.0,"zaman_farki":435},{"takim_numarasi":18,"iha_enlem":40.2313576,"iha_boylam":29.009079,"iha_irtifa":-0.071,"iha_dikilme":-11.1925449,"iha_yonelme":353.710541,"iha_yatis":12.1959143,"iha_hizi":0.02,"zaman_farki":1209383},{"takim_numarasi":22,"iha_enlem":40.2305679,"iha_boylam":29.0075417,"iha_irtifa":-2.0,"iha_dikilme":-4.0,"iha_yonelme":243.0,"iha_yatis":-1.0,"iha_hizi":0.0,"zaman_farki":291639}]}
