{"telem": {"takim_numarasi": 9, "iha_enlem": 40.2324989, "iha_boylam": 29.0071226, "iha_irtifa": 78.907, "iha_dikilme": 9.362, "iha_yonelme": 296.0, "iha_yatis": -3.149, "iha_hiz": 8.063, "iha_kilitlenme": 0, "iha_batarya": 70, "iha_otonom": 1, "hedef_merkez_X": 0, "hedef_merkez_Y": 0, "hedef_genislik": 0, "hedef_yukseklik": 0, "gps_saati": {"saat": 11, "dakika": 6, "saniye": 9, "milisaniye": 800}, "IHA_kilitlenme": 0}, "Others": {"Servo": {"Servo1": 1462, "Servo2": 1304, "Servo3": 1485, "Servo4": 1666, "Servo5": 1462, "Servo6": 0, "Servo7": 0, "Servo8": 0}, "Channel": {"Channel1": 1488, "Channel2": 1400, "Channel3": 1528, "Channel4": 1496, "Channel5": 992, "Channel6": 992, "Channel7": 1996, "Channel8": 1560}, "WindData": {"WindSpeed": 7.469996929168701, "WindDirection": 307.4200439453125}, "Mode": "AUTO"}, "uniData": {"Heading": 296.0, "Roll": -3.149, "VerticalSpeed": 2.271, "AirSpeed": 13.934}}
