{"telem": {"takim_numarasi": 9, "iha_enlem": 40.2318832, "iha_boylam": 29.0059376, "iha_irtifa": 102.529, "iha_dikilme": 4.622, "iha_yonelme": 10.0, "iha_yatis": -0.752, "iha_hiz": 9.784, "iha_kilitlenme": 0, "iha_batarya": 60, "iha_otonom": 1, "hedef_merkez_X": 0, "hedef_merkez_Y": 0, "hedef_genislik": 0, "hedef_yukseklik": 0, "gps_saati": {"saat": 11, "dakika": 12, "saniye": 18, "milisaniye": 277}, "IHA_kilitlenme": 0}, "Others": {"Servo": {"Servo1": 1572, "Servo2": 1426, "Servo3": 1330, "Servo4": 1602, "Servo5": 1572, "Servo6": 0, "Servo7": 0, "Servo8": 0}, "Channel": {"Channel1": 1499, "Channel2": 1499, "Channel3": 1483, "Channel4": 1460, "Channel5": 1996, "Channel6": 992, "Channel7": 1996, "Channel8": 1560}, "WindData": {"WindSpeed": 5.837501049041748, "WindDirection": 353.8713765144348}, "Mode": "GUIDED"}, "uniData": {"Heading": 10.0, "Roll": -0.752, "VerticalSpeed": 1.348, "AirSpeed": 16.762}}
