{"telem": {"takim_numarasi": 9, "iha_enlem": 40.2322867, "iha_boylam": 29.0078242, "iha_irtifa": 77.673, "iha_dikilme": 10.245, "iha_yonelme": 3.0, "iha_yatis": -2.858, "iha_hiz": 6.766, "iha_kilitlenme": 0, "iha_batarya": 34, "iha_otonom": 1, "hedef_merkez_X": 0, "hedef_merkez_Y": 0, "hedef_genislik": 0, "hedef_yukseklik": 0, "gps_saati": {"saat": 11, "dakika": 24, "saniye": 17, "milisaniye": 777}, "IHA_kilitlenme": 0}, "Others": {"Servo": {"Servo1": 1570, "Servo2": 1325, "Servo3": 1456, "Servo4": 1699, "Servo5": 1570, "Servo6": 0, "Servo7": 0, "Servo8": 0}, "Channel": {"Channel1": 1488, "Channel2": 1416, "Channel3": 1528, "Channel4": 1496, "Channel5": 992, "Channel6": 992, "Channel7": 1996, "Channel8": 1560}, "WindData": {"WindSpeed": 8.474020004272461, "WindDirection": 357.9915883541107}, "Mode": "AUTO"}, "uniData": {"Heading": 3.0, "Roll": -2.858, "VerticalSpeed": 2.68, "AirSpeed": 14.878}}
