{"sunucusaati":{"gun":17,"saat":8,"dakika":47,"saniye":48,"milisaniye":583},"konumBilgileri":[{"takim_numarasi":1,"iha_enlem":40.231636,"iha_boylam":29.0090923,"iha_irtifa":0.66,"iha_dikilme":11.71,"iha_yonelme":355.64,"iha_yatis":30.19,"iha_hizi":1.28,"zaman_farki":404424},{"takim_numarasi":8,"iha_enlem":40.23193,"iha_boylam":29.00668,"iha_irtifa":98.841,"iha_dikilme":2.9835577,"iha_yonelme":100.88,"iha_yatis":34.13975,"iha_hizi":18.99,"zaman_farki":531},{"takim_numarasi":10,"iha_enlem":40.2316971,"iha_boylam":29.0089722,"iha_irtifa":66.6,"iha_dikilme":-2.0,"iha_yonelme":198.0,"iha_yatis":2.0,"iha_hizi":63.0,"zaman_farki":-38},{"takim_numarasi":12,"iha_enlem":40.2328148,"iha_boylam":29.009037,"iha_irtifa":0.0,"iha_dikilme":-19.0,"iha_yonelme":265.0,"iha_yatis":4.0,"iha_hizi":1.0,"zaman_farki":53519},{"takim_numarasi":13,"iha_enlem":40.2316628,"iha_boylam":29.00756,"iha_irtifa":60.78,"iha_dikilme":-4.622869,"iha_yonelme":184.693832,"iha_yatis":41.1523628,"iha_hizi":24.1274319,"zaman_farki":-15},{"takim_numarasi":14,"iha_enlem":40.2330132,"iha_boylam":29.0068188,"iha_irtifa":102.862,"iha_dikilme":1.0,"iha_yonelme":106.0,"iha_yatis":55.0,"iha_hizi":27.0,"zaman_farki":1246},{"takim_numarasi":22,"iha_enlem":40.231514,"iha_boylam":29.009346,"iha_irtifa":0.0,"iha_dikilme":0.0,"iha_yonelme":60.0,"iha_yatis":0.0,"iha_hizi":0.0,"zaman_farki":31668583}]}
