{"sunucusaati":{"gun":19,"saat":11,"dakika":18,"saniye":56,"milisaniye":218},"konumBilgileri":[{"takim_numarasi":2,"iha_enlem":40.2313538,"iha_boylam":29.0091553,"iha_irtifa":0.086,"iha_dikilme":-16.3249435,"iha_yonelme":125.764725,"iha_yatis":-12.4303493,"iha_hizi":1.0,"zaman_farki":661873},{"takim_numarasi":4,"iha_enlem":40.23179,"iha_boylam":29.0093327,"iha_irtifa":0.029,"iha_dikilme":1.0,"iha_yonelme":155.0,"iha_yatis":1.0,"iha_hizi":0.0,"zaman_farki":1557666},{"takim_numarasi":6,"iha_enlem":40.2309952,"iha_boylam":29.0088024,"iha_irtifa":3.0,"iha_dikilme":-24.0,"iha_yonelme":358.0,"iha_yatis":-13.0,"iha_hizi":22.0,"zaman_farki":570545},{"takim_numarasi":8,"iha_enlem":40.232048,"iha_boylam":29.008934,"iha_irtifa":-2.075,"iha_dikilme":14.5076618,"iha_yonelme":356.59,"iha_yatis":-0.799563766,"iha_hizi":0.5,"zaman_farki":154266},{"takim_numarasi":10,"iha_enlem":40.2321053,"iha_boylam":29.0080833,"iha_irtifa":64.8,"iha_dikilme":-3.0,"iha_yonelme":125.0,"iha_yatis":30.0,"iha_hizi":75.0,"zaman_farki":367},{"takim_numarasi":11,"iha_enlem":40.2323456,"iha_boylam":29.0076122,"iha_irtifa":154.0,"iha_dikilme":-1.0,"iha_yonelme":7.0,"iha_yatis":0.0,"iha_hizi":17.0,"zaman_farki":510},{"takim_numarasi":12,"iha_enlem":40.2310333,"iha_boylam":29.0069942,"iha_irtifa":62.0,"iha_dikilme":3.0,"iha_yonelme":322.0,"iha_yatis":21.0,"iha_hizi":14.0,"zaman_farki":944},{"takim_numarasi":13,"iha_enlem":40.2327232,"iha_boylam":29.0047722,"iha_irtifa":57.64,"iha_dikilme":-0.5041801,"iha_yonelme":3.063142,"iha_yatis":3.17552018,"iha_hizi":11.4453754,"zaman_farki":1354},{"takim_numarasi":14,"iha_enlem":40.2306633,"iha_boylam":29.0067654,"iha_irtifa":91.638,"iha_dikilme":2.0,"iha_yonelme":259.0,"iha_yatis":42.0,"iha_hizi":23.0,"zaman_farki":-191},{"takim_numarasi":18,"iha_enlem":40.2309227,"iha_boylam":29.0076637,"iha_irtifa":81.145,"iha_dikilme":-5.86945152,"iha_yonelme":16.4469528,"iha_yatis":-31.9680138,"iha_hizi":17.1099987,"zaman_farki":646},{"takim_numarasi":20,"iha_enlem":40.23138,"iha_boylam":29.00933,"iha_irtifa":0.0,"iha_dikilme":-2.0,"iha_yonelme":316.0,"iha_yatis":-11.0,"iha_hizi":0.0,"zaman_farki":-301},{"takim_numarasi":22,"iha_enlem":40.2312126,"iha_boylam":29.00602,"iha_irtifa":91.0,"iha_dikilme":1.0,"iha_yonelme":314.0,"iha_yatis":6.0,"iha_hizi":7.0,"zaman_farki":297}]}
