{"sunucusaati":{"gun":19,"saat":11,"dakika":24,"saniye":58,"milisaniye":527},"konumBilgileri":[{"takim_numarasi":2,"iha_enlem":40.2313538,"iha_boylam":29.0091553,"iha_irtifa":0.086,"iha_dikilme":-16.3249435,"iha_yonelme":125.764725,"iha_yatis":-12.4303493,"iha_hizi":1.0,"zaman_farki":1024182},{"takim_numarasi":4,"iha_enlem":40.23179,"iha_boylam":29.0093327,"iha_irtifa":0.029,"iha_dikilme":1.0,"iha_yonelme":155.0,"iha_yatis":1.0,"iha_hizi":0.0,"zaman_farki":1919975},{"takim_numarasi":6,"iha_enlem":40.2309952,"iha_boylam":29.0088024,"iha_irtifa":3.0,"iha_dikilme":-24.0,"iha_yonelme":358.0,"iha_yatis":-13.0,"iha_hizi":22.0,"zaman_farki":932854},{"takim_numarasi":8,"iha_enlem":40.232048,"iha_boylam":29.008934,"iha_irtifa":-2.075,"iha_dikilme":14.5076618,"iha_yonelme":356.59,"iha_yatis":-0.799563766,"iha_hizi":0.5,"zaman_farki":516575},{"takim_numarasi":10,"iha_enlem":40.2318764,"iha_boylam":29.00817,"iha_irtifa":13.3,"iha_dikilme":-4.0,"iha_yonelme":31.0,"iha_yatis":-19.0,"iha_hizi":42.0,"zaman_farki":138699},{"takim_numarasi":11,"iha_enlem":40.2314568,"iha_boylam":29.00783,"iha_irtifa":96.0,"iha_dikilme":5.0,"iha_yonelme":5.0,"iha_yatis":7.0,"iha_hizi":19.0,"zaman_farki":198},{"takim_numarasi":12,"iha_enlem":40.2314072,"iha_boylam":29.0081177,"iha_irtifa":33.0,"iha_dikilme":-8.0,"iha_yonelme":235.0,"iha_yatis":25.0,"iha_hizi":17.0,"zaman_farki":753},{"takim_numarasi":13,"iha_enlem":40.2312,"iha_boylam":29.00371,"iha_irtifa":57.18,"iha_dikilme":-1.51795566,"iha_yonelme":248.621979,"iha_yatis":42.1015778,"iha_hizi":22.11159,"zaman_farki":963},{"takim_numarasi":14,"iha_enlem":40.2306747,"iha_boylam":29.0064735,"iha_irtifa":72.502,"iha_dikilme":12.0,"iha_yonelme":191.0,"iha_yatis":25.0,"iha_hizi":23.0,"zaman_farki":-147},{"takim_numarasi":18,"iha_enlem":40.23136,"iha_boylam":29.0092754,"iha_irtifa":0.825,"iha_dikilme":-24.0224361,"iha_yonelme":86.11819,"iha_yatis":-43.54921,"iha_hizi":1.81,"zaman_farki":196},{"takim_numarasi":20,"iha_enlem":40.23138,"iha_boylam":29.00933,"iha_irtifa":0.0,"iha_dikilme":-2.0,"iha_yonelme":316.0,"iha_yatis":-11.0,"iha_hizi":0.0,"zaman_farki":208},{"takim_numarasi":22,"iha_enlem":40.2320137,"iha_boylam":29.00786,"iha_irtifa":67.0,"iha_dikilme":7.0,"iha_yonelme":254.0,"iha_yatis":50.0,"iha_hizi":17.0,"zaman_farki":482}]}
