{"telem": {"takim_numarasi": 9, "iha_enlem": 40.2310586, "iha_boylam": 29.0065604, "iha_irtifa": 80.382, "iha_dikilme": 5.618, "iha_yonelme": 72.0, "iha_yatis": 16.451, "iha_hiz": 15.559, "iha_kilitlenme": 0, "iha_batarya": 72, "iha_otonom": 1, "hedef_merkez_X": 0, "hedef_merkez_Y": 0, "hedef_genislik": 0, "hedef_yukseklik": 0, "gps_saati": {"saat": 14, "dakika": 19, "saniye": 37, "milisaniye": 143}, "IHA_kilitlenme": 0}, "Others": {"Servo": {"Servo1": 1462, "Servo2": 1408, "Servo3": 1420, "Servo4": 1553, "Servo5": 1462, "Servo6": 0, "Servo7": 0, "Servo8": 0}, "Channel": {"Channel1": 1496, "Channel2": 1476, "Channel3": 1476, "Channel4": 1500, "Channel5": 992, "Channel6": 992, "Channel7": 1996, "Channel8": 1560}, "WindData": {"WindSpeed": 3.0076920986175537, "WindDirection": 24.099117279052734}, "Mode": "AUTO"}, "uniData": {"Heading": 72.0, "Roll": 16.451, "VerticalSpeed": 1.7, "AirSpeed": 17.256}}
