{"telem": {"takim_numarasi": 9, "iha_enlem": 40.2323213, "iha_boylam": 29.0078474, "iha_irtifa": 79.719, "iha_dikilme": 5.13, "iha_yonelme": 10.0, "iha_yatis": -9.132, "iha_hiz": 12.049, "iha_kilitlenme": 0, "iha_batarya": 67, "iha_otonom": 1, "hedef_merkez_X": 0, "hedef_merkez_Y": 0, "hedef_genislik": 0, "hedef_yukseklik": 0, "gps_saati": {"saat": 14, "dakika": 23, "saniye": 16, "milisaniye": 642}, "IHA_kilitlenme": 0}, "Others": {"Servo": {"Servo1": 1817, "Servo2": 1441, "Servo3": 1379, "Servo4": 1726, "Servo5": 1817, "Servo6": 0, "Servo7": 0, "Servo8": 0}, "Channel": {"Channel1": 1496, "Channel2": 1472, "Channel3": 1476, "Channel4": 1500, "Channel5": 992, "Channel6": 992, "Channel7": 1996, "Channel8": 1560}, "WindData": {"WindSpeed": 3.429913282394409, "WindDirection": 25.040283203125}, "Mode": "AUTO"}, "uniData": {"Heading": 10.0, "Roll": -9.132, "VerticalSpeed": 1.394, "AirSpeed": 15.772}}
