{"sunucusaati":{"gun":17,"saat":14,"dakika":17,"saniye":43,"milisaniye":774},"konumBilgileri":[{"takim_numarasi":6,"iha_enlem":40.23011,"iha_boylam":29.00695,"iha_irtifa":11.0,"iha_dikilme":17.0,"iha_yonelme":61.0,"iha_yatis":-54.0,"iha_hizi":28.0,"zaman_farki":-658},{"takim_numarasi":8,"iha_enlem":40.2321243,"iha_boylam":29.0072689,"iha_irtifa":90.891,"iha_dikilme":1.983183,"iha_yonelme":189.45,"iha_yatis":-44.3305359,"iha_hizi":20.53,"zaman_farki":-223},{"takim_numarasi":10,"iha_enlem":40.23229,"iha_boylam":29.0074,"iha_irtifa":69.0,"iha_dikilme":0.0,"iha_yonelme":5.0,"iha_yatis":34.0,"iha_hizi":58.0,"zaman_farki":-100},{"takim_numarasi":12,"iha_enlem":40.2317047,"iha_boylam":29.00617,"iha_irtifa":51.0,"iha_dikilme":5.0,"iha_yonelme":330.0,"iha_yatis":31.0,"iha_hizi":19.0,"zaman_farki":500},{"takim_numarasi":13,"iha_enlem":40.2322464,"iha_boylam":29.0039768,"iha_irtifa":99.15,"iha_dikilme":1.17509067,"iha_yonelme":66.30014,"iha_yatis":35.16736,"iha_hizi":20.11023,"zaman_farki":332},{"takim_numarasi":14,"iha_enlem":40.2309,"iha_boylam":29.0057259,"iha_irtifa":82.01,"iha_dikilme":0.0,"iha_yonelme":214.0,"iha_yatis":56.0,"iha_hizi":28.0,"zaman_farki":198},{"takim_numarasi":15,"iha_enlem":40.2321777,"iha_boylam":29.0073051,"iha_irtifa":67.0,"iha_dikilme":-2.0,"iha_yonelme":181.0,"iha_yatis":-59.0,"iha_hizi":24.0,"zaman_farki":238},{"takim_numarasi":22,"iha_enlem":40.231678,"iha_boylam":29.00744,"iha_irtifa":98.0,"iha_dikilme":19.0,"iha_yonelme":108.0,"iha_yatis":-2.0,"iha_hizi":13.0,"zaman_farki":278}]}
