{"sunucusaati":{"gun":17,"saat":14,"dakika":30,"saniye":29,"milisaniye":748},"konumBilgileri":[{"takim_numarasi":6,"iha_enlem":40.2314,"iha_boylam":29.0090485,"iha_irtifa":0.0,"iha_dikilme":12.0,"iha_yonelme":2.0,"iha_yatis":-37.0,"iha_hizi":2.0,"zaman_farki":490894},{"takim_numarasi":8,"iha_enlem":40.2317657,"iha_boylam":29.0079136,"iha_irtifa":84.545,"iha_dikilme":7.169963,"iha_yonelme":213.46,"iha_yatis":39.424427,"iha_hizi":17.27,"zaman_farki":-249},{"takim_numarasi":10,"iha_enlem":40.2324753,"iha_boylam":29.0083714,"iha_irtifa":71.5,"iha_dikilme":0.0,"iha_yonelme":102.0,"iha_yatis":-1.0,"iha_hizi":72.0,"zaman_farki":748},{"takim_numarasi":12,"iha_enlem":40.23099,"iha_boylam":29.0068855,"iha_irtifa":48.0,"iha_dikilme":4.0,"iha_yonelme":304.0,"iha_yatis":22.0,"iha_hizi":17.0,"zaman_farki":7474},{"takim_numarasi":13,"iha_enlem":40.23174,"iha_boylam":29.0063725,"iha_irtifa":90.73,"iha_dikilme":3.39000416,"iha_yonelme":290.302277,"iha_yatis":-28.63753,"iha_hizi":18.1870327,"zaman_farki":884},{"takim_numarasi":14,"iha_enlem":40.2319527,"iha_boylam":29.008009,"iha_irtifa":79.337,"iha_dikilme":0.0,"iha_yonelme":181.0,"iha_yatis":48.0,"iha_hizi":26.0,"zaman_farki":-292},{"takim_numarasi":15,"iha_enlem":40.2323227,"iha_boylam":29.0082111,"iha_irtifa":70.0,"iha_dikilme":-2.0,"iha_yonelme":271.0,"iha_yatis":46.0,"iha_hizi":20.0,"zaman_farki":741625},{"takim_numarasi":22,"iha_enlem":40.23132,"iha_boylam":29.0057125,"iha_irtifa":89.0,"iha_dikilme":-1.0,"iha_yonelme":247.0,"iha_yatis":38.0,"iha_hizi":20.0,"zaman_farki":169}]}
