{"telem": {"takim_numarasi": 9, "iha_enlem": 40.230814, "iha_boylam": 29.0077795, "iha_irtifa": 76.692, "iha_dikilme": 11.608, "iha_yonelme": 101.0, "iha_yatis": -32.776, "iha_hiz": 19.296, "iha_kilitlenme": 0, "iha_batarya": 38, "iha_otonom": 1, "hedef_merkez_X": 0, "hedef_merkez_Y": 0, "hedef_genislik": 0, "hedef_yukseklik": 0, "gps_saati": {"saat": 8, "dakika": 57, "saniye": 29, "milisaniye": 964}, "IHA_kilitlenme": 0}, "Others": {"Servo": {"Servo1": 1767, "Servo2": 1403, "Servo3": 1560, "Servo4": 1726, "Servo5": 1767, "Servo6": 0, "Servo7": 0, "Servo8": 0}, "Channel": {"Channel1": 1492, "Channel2": 1452, "Channel3": 1552, "Channel4": 1496, "Channel5": 992, "Channel6": 992, "Channel7": 1996, "Channel8": 1560}, "WindData": {"WindSpeed": 4.3598480224609375, "WindDirection": 257.5920181274414}, "Mode": "AUTO"}, "uniData": {"Heading": 101.0, "Roll": -32.776, "VerticalSpeed": 3.397, "AirSpeed": 17.401}}
