{"telem": {"takim_numarasi": 9, "iha_enlem": 40.2310799, "iha_boylam": 29.0081915, "iha_irtifa": 76.356, "iha_dikilme": 9.207, "iha_yonelme": 327.0, "iha_yatis": -38.881, "iha_hiz": 14.433, "iha_kilitlenme": 0, "iha_batarya": 29, "iha_otonom": 1, "hedef_merkez_X": 0, "hedef_merkez_Y": 0, "hedef_genislik": 0, "hedef_yukseklik": 0, "gps_saati": {"saat": 9, "dakika": 4, "saniye": 11, "milisaniye": 730}, "IHA_kilitlenme": 0}, "Others": {"Servo": {"Servo1": 1343, "Servo2": 1322, "Servo3": 1536, "Servo4": 1586, "Servo5": 1343, "Servo6": 0, "Servo7": 0, "Servo8": 0}, "Channel": {"Channel1": 1488, "Channel2": 1452, "Channel3": 1552, "Channel4": 1496, "Channel5": 992, "Channel6": 992, "Channel7": 1996, "Channel8": 1560}, "WindData": {"WindSpeed": 3.7987661361694336, "WindDirection": 267.3192901611328}, "Mode": "AUTO"}, "uniData": {"Heading": 327.0, "Roll": -38.881, "VerticalSpeed": 2.853, "AirSpeed": 17.605}}
