{"sunucusaati":{"gun":19,"saat":8,"dakika":40,"saniye":32,"milisaniye":850},"konumBilgileri":[{"takim_numarasi":1,"iha_enlem":40.23148,"iha_boylam":29.00903,"iha_irtifa":0.33,"iha_dikilme":1.55,"iha_yonelme":17.19,"iha_yatis":-1.46,"iha_hizi":0.05,"zaman_farki":824},{"takim_numarasi":4,"iha_enlem":40.2321358,"iha_boylam":29.0087681,"iha_irtifa":-0.443,"iha_dikilme":-21.0,"iha_yonelme":348.0,"iha_yatis":2.0,"iha_hizi":0.0,"zaman_farki":4363},{"takim_numarasi":6,"iha_enlem":40.2313843,"iha_boylam":29.0090389,"iha_irtifa":0.0,"iha_dikilme":-2.0,"iha_yonelme":354.0,"iha_yatis":17.0,"iha_hizi":0.0,"zaman_farki":375},{"takim_numarasi":8,"iha_enlem":40.2317276,"iha_boylam":29.0090218,"iha_irtifa":-0.32,"iha_dikilme":13.5499763,"iha_yonelme":8.3,"iha_yatis":-1.77186477,"iha_hizi":0.36,"zaman_farki":118},{"takim_numarasi":10,"iha_enlem":40.2315826,"iha_boylam":29.0090485,"iha_irtifa":6.7,"iha_dikilme":0.0,"iha_yonelme":269.0,"iha_yatis":0.0,"iha_hizi":0.0,"zaman_farki":321},{"takim_numarasi":12,"iha_enlem":40.2318573,"iha_boylam":29.0090084,"iha_irtifa":0.0,"iha_dikilme":2.0,"iha_yonelme":323.0,"iha_yatis":-1.0,"iha_hizi":13.0,"zaman_farki":390},{"takim_numarasi":13,"iha_enlem":40.23124,"iha_boylam":29.0090466,"iha_irtifa":-2.75,"iha_dikilme":7.679189,"iha_yonelme":17.8650818,"iha_yatis":-4.64000368,"iha_hizi":0.0228385814,"zaman_farki":833},{"takim_numarasi":14,"iha_enlem":40.231678,"iha_boylam":29.0090618,"iha_irtifa":-0.068,"iha_dikilme":0.0,"iha_yonelme":7.0,"iha_yatis":1.0,"iha_hizi":0.0,"zaman_farki":668},{"takim_numarasi":15,"iha_enlem":40.2314224,"iha_boylam":29.0090446,"iha_irtifa":-8.0,"iha_dikilme":-26.0,"iha_yonelme":212.0,"iha_yatis":13.0,"iha_hizi":0.0,"zaman_farki":24289},{"takim_numarasi":17,"iha_enlem":40.2315178,"iha_boylam":29.008997,"iha_irtifa":4.0,"iha_dikilme":12.0,"iha_yonelme":253.0,"iha_yatis":0.0,"iha_hizi":0.0,"zaman_farki":1041},{"takim_numarasi":18,"iha_enlem":40.23134,"iha_boylam":29.0090618,"iha_irtifa":-0.04,"iha_dikilme":-1.24463284,"iha_yonelme":195.454819,"iha_yatis":14.8544817,"iha_hizi":0.87,"zaman_farki":831},{"takim_numarasi":19,"iha_enlem":40.23161,"iha_boylam":29.0091724,"iha_irtifa":0.0,"iha_dikilme":11.0,"iha_yonelme":52.0,"iha_yatis":-2.0,"iha_hizi":0.0,"zaman_farki":1648},{"takim_numarasi":20,"iha_enlem":40.23117,"iha_boylam":29.00905,"iha_irtifa":-1.0,"iha_dikilme":1.0,"iha_yonelme":246.0,"iha_yatis":0.0,"iha_hizi":0.0,"zaman_farki":913}]}
