{"sunucusaati":{"gun":19,"saat":8,"dakika":47,"saniye":57,"milisaniye":669},"konumBilgileri":[{"takim_numarasi":1,"iha_enlem":40.2311,"iha_boylam":29.0077324,"iha_irtifa":75.47,"iha_dikilme":4.82,"iha_yonelme":254.61,"iha_yatis":25.64,"iha_hizi":13.93,"zaman_farki":1642},{"takim_numarasi":4,"iha_enlem":40.2321358,"iha_boylam":29.0087681,"iha_irtifa":-0.443,"iha_dikilme":-21.0,"iha_yonelme":348.0,"iha_yatis":2.0,"iha_hizi":0.0,"zaman_farki":449182},{"takim_numarasi":6,"iha_enlem":40.2311668,"iha_boylam":29.0080166,"iha_irtifa":107.0,"iha_dikilme":13.0,"iha_yonelme":231.0,"iha_yatis":23.0,"iha_hizi":10.0,"zaman_farki":0},{"takim_numarasi":8,"iha_enlem":40.2311821,"iha_boylam":29.0069447,"iha_irtifa":107.777,"iha_dikilme":7.115297,"iha_yonelme":333.3,"iha_yatis":31.981348,"iha_hizi":18.78,"zaman_farki":-62},{"takim_numarasi":10,"iha_enlem":40.2313,"iha_boylam":29.0085869,"iha_irtifa":63.5,"iha_dikilme":4.0,"iha_yonelme":209.0,"iha_yatis":-8.0,"iha_hizi":54.0,"zaman_farki":71},{"takim_numarasi":11,"iha_enlem":40.2316742,"iha_boylam":29.0090351,"iha_irtifa":0.0,"iha_dikilme":0.0,"iha_yonelme":314.0,"iha_yatis":0.0,"iha_hizi":3.0,"zaman_farki":260621},{"takim_numarasi":12,"iha_enlem":40.23022,"iha_boylam":29.0080929,"iha_irtifa":50.0,"iha_dikilme":12.0,"iha_yonelme":282.0,"iha_yatis":18.0,"iha_hizi":16.0,"zaman_farki":449},{"takim_numarasi":13,"iha_enlem":40.2312164,"iha_boylam":29.0066433,"iha_irtifa":60.27,"iha_dikilme":-3.13819027,"iha_yonelme":229.600784,"iha_yatis":17.35047,"iha_hizi":16.3131447,"zaman_farki":152},{"takim_numarasi":14,"iha_enlem":40.2317047,"iha_boylam":29.006958,"iha_irtifa":59.651,"iha_dikilme":-3.0,"iha_yonelme":198.0,"iha_yatis":32.0,"iha_hizi":22.0,"zaman_farki":486},{"takim_numarasi":15,"iha_enlem":40.2323532,"iha_boylam":29.0079517,"iha_irtifa":42.0,"iha_dikilme":3.0,"iha_yonelme":278.0,"iha_yatis":-59.0,"iha_hizi":13.0,"zaman_farki":745},{"takim_numarasi":17,"iha_enlem":40.23065,"iha_boylam":29.0074062,"iha_irtifa":52.0,"iha_dikilme":-1.0,"iha_yonelme":155.0,"iha_yatis":-27.0,"iha_hizi":23.0,"zaman_farki":5422},{"takim_numarasi":18,"iha_enlem":40.23232,"iha_boylam":29.00762,"iha_irtifa":121.259,"iha_dikilme":-1.3322655,"iha_yonelme":265.766724,"iha_yatis":10.6169815,"iha_hizi":14.25,"zaman_farki":606},{"takim_numarasi":19,"iha_enlem":40.23214,"iha_boylam":29.0098076,"iha_irtifa":-2.0,"iha_dikilme":-26.0,"iha_yonelme":109.0,"iha_yatis":60.0,"iha_hizi":37.0,"zaman_farki":348964},{"takim_numarasi":20,"iha_enlem":40.2314339,"iha_boylam":29.002512,"iha_irtifa":72.0,"iha_dikilme":-8.0,"iha_yonelme":278.0,"iha_yatis":19.0,"iha_hizi":11.0,"zaman_farki":1132}]}
