{"telem": {"takim_numarasi": 34, "iha_enlem": 40.231441, "iha_boylam": 29.006855, "iha_irtifa": 59.572, "iha_dikilme": 15.452, "iha_yonelme": 278.0, "iha_yatis": 1.141, "iha_hiz": 16.758, "iha_kilitlenme": 0, "iha_batarya": 63, "iha_otonom": 1, "hedef_merkez_X": 0, "hedef_merkez_Y": 0, "hedef_genislik": 0, "hedef_yukseklik": 0, "gps_saati": {"saat": 8, "dakika": 42, "saniye": 1, "milisaniye": 13}, "IHA_kilitlenme": 0}, "Others": {"Servo": {"Servo1": 1514, "Servo2": 1469, "Servo3": 1655, "Servo4": 1551, "Servo5": 1514, "Servo6": 0, "Servo7": 0, "Servo8": 0}, "Channel": {"Channel1": 1516, "Channel2": 1508, "Channel3": 1512, "Channel4": 1508, "Channel5": 992, "Channel6": 992, "Channel7": 1996, "Channel8": 1560}, "WindData": {"WindSpeed": 4.397501468658447, "WindDirection": 305.92746353149414}, "Mode": "AUTO"}, "uniData": {"Heading": 278.0, "Roll": 1.141, "VerticalSpeed": 5.419, "AirSpeed": 20.105}}
