{"telem": {"takim_numarasi": 34, "iha_enlem": 40.2309727, "iha_boylam": 29.0053167, "iha_irtifa": 70.582, "iha_dikilme": 4.159, "iha_yonelme": 254.0, "iha_yatis": 1.962, "iha_hiz": 10.792, "iha_kilitlenme": 0, "iha_batarya": 45, "iha_otonom": 1, "hedef_merkez_X": 0, "hedef_merkez_Y": 0, "hedef_genislik": 0, "hedef_yukseklik": 0, "gps_saati": {"saat": 9, "dakika": 2, "saniye": 9, "milisaniye": 770}, "IHA_kilitlenme": 0}, "Others": {"Servo": {"Servo1": 1457, "Servo2": 1324, "Servo3": 1362, "Servo4": 1659, "Servo5": 1457, "Servo6": 0, "Servo7": 0, "Servo8": 0}, "Channel": {"Channel1": 1500, "Channel2": 1496, "Channel3": 1508, "Channel4": 1500, "Channel5": 992, "Channel6": 992, "Channel7": 1996, "Channel8": 1560}, "WindData": {"WindSpeed": 4.132843971252441, "WindDirection": 259.7974395751953}, "Mode": "AUTO"}, "uniData": {"Heading": 254.0, "Roll": 1.962, "VerticalSpeed": 1.122, "AirSpeed": 15.418}}
