{"telem": {"takim_numarasi": 34, "iha_enlem": 40.2310422, "iha_boylam": 29.0089907, "iha_irtifa": 3.024, "iha_dikilme": -9.516, "iha_yonelme": 7.0, "iha_yatis": -7.522, "iha_hiz": 15.908, "iha_kilitlenme": 0, "iha_batarya": 54, "iha_otonom": 1, "hedef_merkez_X": 0, "hedef_merkez_Y": 0, "hedef_genislik": 0, "hedef_yukseklik": 0, "gps_saati": {"saat": 9, "dakika": 3, "saniye": 44, "milisaniye": 13}, "IHA_kilitlenme": 0}, "Others": {"Servo": {"Servo1": 1539, "Servo2": 1376, "Servo3": 1100, "Servo4": 1645, "Servo5": 1539, "Servo6": 0, "Servo7": 0, "Servo8": 0}, "Channel": {"Channel1": 1508, "Channel2": 1500, "Channel3": 1508, "Channel4": 1500, "Channel5": 992, "Channel6": 992, "Channel7": 1996, "Channel8": 1560}, "WindData": {"WindSpeed": 3.2990381717681885, "WindDirection": 296.1867485046387}, "Mode": "AUTO"}, "uniData": {"Heading": 7.0, "Roll": -7.522, "VerticalSpeed": -2.724, "AirSpeed": 16.658}}
