{"telem": {"takim_numarasi": 34, "iha_enlem": 40.232338, "iha_boylam": 29.0067486, "iha_irtifa": 79.092, "iha_dikilme": 3.867, "iha_yonelme": 243.0, "iha_yatis": 10.966, "iha_hiz": 12.07, "iha_kilitlenme": 0, "iha_batarya": 80, "iha_otonom": 1, "hedef_merkez_X": 0, "hedef_merkez_Y": 0, "hedef_genislik": 0, "hedef_yukseklik": 0, "gps_saati": {"saat": 12, "dakika": 38, "saniye": 34, "milisaniye": 533}, "IHA_kilitlenme": 0}, "Others": {"Servo": {"Servo1": 1471, "Servo2": 1368, "Servo3": 1385, "Servo4": 1617, "Servo5": 1471, "Servo6": 0, "Servo7": 0, "Servo8": 0}, "Channel": {"Channel1": 1512, "Channel2": 1484, "Channel3": 1528, "Channel4": 1500, "Channel5": 992, "Channel6": 992, "Channel7": 1996, "Channel8": 1560}, "WindData": {"WindSpeed": 4.905591011047363, "WindDirection": 263.59178161621094}, "Mode": "AUTO"}, "uniData": {"Heading": 243.0, "Roll": 10.966, "VerticalSpeed": 1.177, "AirSpeed": 17.343}}
