{"telem": {"takim_numarasi": 34, "iha_enlem": 40.2324006, "iha_boylam": 29.004542, "iha_irtifa": 78.977, "iha_dikilme": 2.053, "iha_yonelme": 255.0, "iha_yatis": -3.35, "iha_hiz": 14.561, "iha_kilitlenme": 0, "iha_batarya": 50, "iha_otonom": 1, "hedef_merkez_X": 0, "hedef_merkez_Y": 0, "hedef_genislik": 0, "hedef_yukseklik": 0, "gps_saati": {"saat": 12, "dakika": 50, "saniye": 37, "milisaniye": 293}, "IHA_kilitlenme": 0}, "Others": {"Servo": {"Servo1": 1466, "Servo2": 1382, "Servo3": 1407, "Servo4": 1588, "Servo5": 1466, "Servo6": 0, "Servo7": 0, "Servo8": 0}, "Channel": {"Channel1": 1500, "Channel2": 1392, "Channel3": 1528, "Channel4": 1500, "Channel5": 992, "Channel6": 992, "Channel7": 1996, "Channel8": 1560}, "WindData": {"WindSpeed": 6.087717533111572, "WindDirection": 184.65850830078125}, "Mode": "AUTO"}, "uniData": {"Heading": 255.0, "Roll": -3.35, "VerticalSpeed": 0.609, "AirSpeed": 17.382}}
