{"telem": {"takim_numarasi": 9, "iha_enlem": 40.2308492, "iha_boylam": 29.0088068, "iha_irtifa": 4.982, "iha_dikilme": 0.233, "iha_yonelme": 350.0, "iha_yatis": 15.621, "iha_hiz": 14.843, "iha_kilitlenme": 0, "iha_batarya": 47, "iha_otonom": 1, "hedef_merkez_X": 0, "hedef_merkez_Y": 0, "hedef_genislik": 0, "hedef_yukseklik": 0, "gps_saati": {"saat": 12, "dakika": 0, "saniye": 22, "milisaniye": 843}, "IHA_kilitlenme": 0}, "Others": {"Servo": {"Servo1": 1432, "Servo2": 1344, "Servo3": 1357, "Servo4": 1638, "Servo5": 1432, "Servo6": 0, "Servo7": 0, "Servo8": 0}, "Channel": {"Channel1": 1516, "Channel2": 1520, "Channel3": 1656, "Channel4": 1508, "Channel5": 992, "Channel6": 992, "Channel7": 1996, "Channel8": 1412}, "WindData": {"WindSpeed": 4.38759183883667, "WindDirection": 319.557861328125}, "Mode": "AUTO"}, "uniData": {"Heading": 350.0, "Roll": 15.621, "VerticalSpeed": 0.077, "AirSpeed": 19.157}}
