{"telem": {"takim_numarasi": 34, "iha_enlem": 40.2312967, "iha_boylam": 29.0067994, "iha_irtifa": 82.775, "iha_dikilme": 2.464, "iha_yonelme": 126.0, "iha_yatis": -6.503, "iha_hiz": 15.755, "iha_kilitlenme": 0, "iha_batarya": 58, "iha_otonom": 1, "hedef_merkez_X": 0, "hedef_merkez_Y": 0, "hedef_genislik": 0, "hedef_yukseklik": 0, "gps_saati": {"saat": 14, "dakika": 55, "saniye": 54, "milisaniye": 501}, "IHA_kilitlenme": 0}, "Others": {"Servo": {"Servo1": 1540, "Servo2": 1391, "Servo3": 1420, "Servo4": 1624, "Servo5": 1540, "Servo6": 0, "Servo7": 0, "Servo8": 0}, "Channel": {"Channel1": 1492, "Channel2": 1456, "Channel3": 1496, "Channel4": 1504, "Channel5": 992, "Channel6": 992, "Channel7": 1996, "Channel8": 1560}, "WindData": {"WindSpeed": 5.95697021484375, "WindDirection": 196.66246032714844}, "Mode": "AUTO"}, "uniData": {"Heading": 126.0, "Roll": -6.503, "VerticalSpeed": 0.725, "AirSpeed": 16.641}}
