{"telem": {"takim_numarasi": 34, "iha_enlem": 40.2333721, "iha_boylam": 29.0083553, "iha_irtifa": 27.542, "iha_dikilme": -2.802, "iha_yonelme": 144.0, "iha_yatis": 14.665, "iha_hiz": 12.759, "iha_kilitlenme": 0, "iha_batarya": 59, "iha_otonom": 1, "hedef_merkez_X": 0, "hedef_merkez_Y": 0, "hedef_genislik": 0, "hedef_yukseklik": 0, "gps_saati": {"saat": 15, "dakika": 4, "saniye": 31, "milisaniye": 261}, "IHA_kilitlenme": 0}, "Others": {"Servo": {"Servo1": 1555, "Servo2": 1320, "Servo3": 1117, "Servo4": 1715, "Servo5": 1555, "Servo6": 0, "Servo7": 0, "Servo8": 0}, "Channel": {"Channel1": 1496, "Channel2": 1452, "Channel3": 1492, "Channel4": 1504, "Channel5": 992, "Channel6": 992, "Channel7": 1996, "Channel8": 1560}, "WindData": {"WindSpeed": 3.8528008460998535, "WindDirection": 170.6194610595703}, "Mode": "AUTO"}, "uniData": {"Heading": 144.0, "Roll": 14.665, "VerticalSpeed": -0.74, "AirSpeed": 15.149}}
